CHANGES.rst
MANIFEST.in
README.rst
development.ini
production.ini
setup.cfg
setup.py
ddbmock/__init__.py
ddbmock/config.py
ddbmock/errors.py
ddbmock.egg-info/PKG-INFO
ddbmock.egg-info/SOURCES.txt
ddbmock.egg-info/dependency_links.txt
ddbmock.egg-info/entry_points.txt
ddbmock.egg-info/not-zip-safe
ddbmock.egg-info/requires.txt
ddbmock.egg-info/top_level.txt
ddbmock/database/__init__.py
ddbmock/database/comparison.py
ddbmock/database/db.py
ddbmock/database/item.py
ddbmock/database/key.py
ddbmock/database/table.py
ddbmock/database/storage/__init__.py
ddbmock/database/storage/memory.py
ddbmock/database/storage/sqlite.py
ddbmock/operations/__init__.py
ddbmock/operations/batch_get_item.py
ddbmock/operations/batch_write_item.py
ddbmock/operations/create_table.py
ddbmock/operations/delete_item.py
ddbmock/operations/delete_table.py
ddbmock/operations/describe_table.py
ddbmock/operations/get_item.py
ddbmock/operations/list_tables.py
ddbmock/operations/put_item.py
ddbmock/operations/query.py
ddbmock/operations/scan.py
ddbmock/operations/update_item.py
ddbmock/operations/update_table.py
ddbmock/router/__init__.py
ddbmock/router/boto.py
ddbmock/router/pyramid.py
ddbmock/utils/__init__.py
ddbmock/utils/stat.py
ddbmock/validators/__init__.py
ddbmock/validators/batch_get_item.py
ddbmock/validators/batch_write_item.py
ddbmock/validators/create_table.py
ddbmock/validators/delete_item.py
ddbmock/validators/delete_table.py
ddbmock/validators/describe_table.py
ddbmock/validators/get_item.py
ddbmock/validators/list_tables.py
ddbmock/validators/put_item.py
ddbmock/validators/query.py
ddbmock/validators/scan.py
ddbmock/validators/types.py
ddbmock/validators/update_item.py
ddbmock/validators/update_table.py
docs/Makefile
docs/conf.py
docs/index.rst
docs/make.bat
docs/_include/intro.rst
docs/_static/archi.png
docs/api/database/db.rst
docs/api/database/item.rst
docs/api/database/itemsize.rst
docs/api/database/key.rst
docs/api/database/table.rst
docs/pages/changelog.rst
docs/pages/extending.rst
docs/pages/getting_started.rst
docs/pages/planning.rst
docs/pages/status.rst
tests/__init__.py
tests/functional/__init__.py
tests/functional/boto/__init__.py
tests/functional/boto/test_batch_get_item.py
