Metadata-Version: 1.1
Name: ddbmock
Version: 1.0.3
Summary: Amazon DynamoDB mock implementation
Home-page: https://bitbucket.org/Ludia/dynamodb-mock
Author: Jean-Tiare Le Bigot
Author-email: jtlebigot@socialludia.com
License: UNKNOWN
Keywords: pyramid dynamodb mock planification
Platform: UNKNOWN
Classifier: Topic :: Internet
Classifier: Topic :: Database :: Database Engines/Servers
Classifier: Topic :: Education :: Testing
Classifier: Topic :: Software Development :: Testing
Classifier: Operating System :: OS Independent
Classifier: Intended Audience :: Developers
Classifier: Development Status :: 4 - Beta
Classifier: Programming Language :: Python
Classifier: Programming Language :: Python :: 2.7
Classifier: License :: OSI Approved :: GNU Library or Lesser General Public License (LGPL)
